AutomationFlow/AutomationFlow.py
AutomationFlow/__init__.py
AutomationFlow/default_functions.py
AutomationFlow/defaults.py
AutomationFlow-0.1.1.dist-info/METADATA
AutomationFlow-0.1.1.dist-info/WHEEL
AutomationFlow-0.1.1.dist-info/top_level.txt
AutomationFlow-0.1.1.dist-info/RECORD
