Metadata-Version: 2.1
Name: AutomationFlow
Version: 0.1.1
Summary: A 'literate' script execution framework. Makes writing more readable scripts easier.
Author: gkegke
License: MIT
Project-URL: Homepage, https://github.com/gkegke/AutomationFlow
Keywords: script,execution,framework
Classifier: License :: OSI Approved :: MIT License
Classifier: Programming Language :: Python
Classifier: Programming Language :: Python :: 3
Requires-Python: >=3.8
Requires-Dist: rich
Requires-Dist: loguru
Provides-Extra: dev
Requires-Dist: pytest ; extra == 'dev'
